Metadata-Version: 2.1
Name: fastrl
Version: 0.0.47
Summary: fastrl is a reinforcement learning library that extends Fastai. This project is not affiliated with fastai or Jeremy Howard.
Home-page: https://github.com/josiahls/fastrl/tree/main/
Author: Josiah Laivins, and contributors
Author-email: 
License: Apache Software License 2.0
Keywords: fastrl reinforcement learning rl robotics fastai deep learning machine learning
Classifier: Development Status :: 3 - Alpha
Classifier: Intended Audience :: Developers
Classifier: License :: OSI Approved :: Apache Software License
Classifier: Natural Language :: English
Classifier: Programming Language :: Python :: 3.7
Classifier: Programming Language :: Python :: 3.8
Classifier: Programming Language :: Python :: 3.9
Classifier: Programming Language :: Python :: 3.10
Requires-Python: >=3.7
License-File: LICENSE
Requires-Dist: pip
Requires-Dist: packaging
Requires-Dist: torch (>=1.13.0.dev20220826+cu113)
Requires-Dist: torchdata (>=0.5.0.dev20220826)
Requires-Dist: gym (>=0.26.1)
Requires-Dist: pyopengl
Requires-Dist: pyglet
Requires-Dist: tensorboard
Requires-Dist: pygame
Requires-Dist: pandas
Requires-Dist: scipy
Requires-Dist: sklearn
Requires-Dist: fastcore
Requires-Dist: fastprogress
Requires-Dist: nbformat (<5.*,>=4.2.0)
Provides-Extra: dev
Requires-Dist: gym[all] (>=0.26.1) ; extra == 'dev'
Requires-Dist: jupyterlab ; extra == 'dev'
Requires-Dist: nbdev (>=2.3.*) ; extra == 'dev'
Requires-Dist: pre-commit ; extra == 'dev'
Requires-Dist: ipywidgets ; extra == 'dev'
Requires-Dist: moviepy ; extra == 'dev'
Requires-Dist: pygifsicle ; extra == 'dev'
Requires-Dist: aquirdturtle-collapsible-headings ; extra == 'dev'
Requires-Dist: plotly ; extra == 'dev'
Requires-Dist: matplotlib-inline ; extra == 'dev'
Requires-Dist: wheel ; extra == 'dev'
Requires-Dist: twine ; extra == 'dev'
Requires-Dist: fastdownload ; extra == 'dev'
Requires-Dist: watchdog[watchmedo] ; extra == 'dev'
Requires-Dist: graphviz ; extra == 'dev'
Requires-Dist: typing-extensions (==4.1.1) ; extra == 'dev'
Requires-Dist: spacy (<4) ; extra == 'dev'
